{"plant_slug": "acacia-myrtifolia-f-celastrifolia", "plant_name_scientific": "acacia myrtifolia f. celastrifolia", "plant_url": "herbs/acacia-myrtifolia-f-celastrifolia.html", "title": "acacia myrtifolia f. celastrifolia", "intro": "Acacia myrtifolia f. celastrifolia, also known as the narrow-leaved myrtle or coastal wattle, is a plant species native to Australia. It has been used in traditional medicine for its medicinal properties, particularly for its anti-inflammatory and antimicrobial properties, which may help to soothe skin irritations and wounds. The plant is valued for its health benefits, including reducing fever, relieving digestive issues, and providing antioxidant properties. Acacia myrtifolia f. celastrifolia is often used in herbal preparations such as teas, infusions, and tinctures, which can be applied topically or taken internally to harness its medicinal and health benefits."}