{"plant_slug": "acetosella-ramigera", "plant_name_scientific": "acetosella ramigera", "plant_url": "herbs/acetosella-ramigera.html", "title": "acetosella ramigera", "intro": "Acetosella ramigera, also known as the red-leaved or New Zealand cranberry, is a species of flowering plant in the family Ericaceae. The plant has been used in traditional medicine for its medicinal properties, which include anti-inflammatory and antimicrobial properties, making it useful in treating various health issues. The health benefits of Acetosella ramigera include the potential to reduce inflammation, improve digestive health, and support the immune system. It can be prepared as a tea, tincture, or infused oil, and is often used in herbal remedies to promote overall well-being."}