{"plant_slug": "anthurium-clidemioides", "plant_name_scientific": "anthurium clidemioides", "plant_url": "herbs/anthurium-clidemioides.html", "title": "anthurium clidemioides", "intro": "Anthurium clidemioides, a species of flowering plant in the family Arum, is a type of aroid native to South America. The plant's roots, leaves, and flowers have been traditionally used in herbal medicine, known for their anti-inflammatory, antibacterial, and antifungal properties. The medicinal properties of Anthurium clidemioides have been associated with various health benefits, including wound healing, pain relief, and the treatment of skin conditions such as acne and eczema. Herbal preparations of this plant may be made into teas, infusions, or topical creams, and are often used in traditional medicine to support overall health and well-being."}