{"plant_slug": "astilbe-congesta", "plant_name_scientific": "astilbe congesta", "plant_url": "herbs/astilbe-congesta.html", "title": "astilbe congesta", "intro": "Astilbe congesta is a type of flowering plant that belongs to the Saxifragaceae family, also known as false goat's beard, characterized by its feathery plumes and delicate white or pink flowers. The plant has been used in traditional medicine for its medicinal properties, particularly its diuretic and anti-inflammatory effects, which have been attributed to its high content of flavonoids and phenolic acids. The health benefits of Astilbe congesta include its potential to reduce blood pressure, alleviate menstrual cramps, and exhibit antioxidant and antimicrobial properties. Herbal preparations of Astilbe congesta can be made into teas, infusions, or tinctures, which are often used to promote digestion, soothe respiratory issues, and support the immune system."}