{"plant_slug": "bromus-rubens-var-eufasciculatus", "plant_name_scientific": "bromus rubens var. eufasciculatus", "plant_url": "herbs/bromus-rubens-var-eufasciculatus.html", "title": "bromus rubens var. eufasciculatus", "intro": "Bromus rubens var. eufasciculatus, commonly known as red brome, is a variant of the red brome grass species that is native to parts of Europe, Africa, and Asia. The plant is known for its medicinal properties, which include anti-inflammatory and antioxidant effects. The health benefits of Bromus rubens var. eufasciculatus include its potential to reduce inflammation, improve digestion, and support immune function. Herbal preparations of the plant can be made into teas, infusions, or tinctures, and are often used to alleviate symptoms of colds, fever, and respiratory issues."}