{"plant_slug": "chondrophora-virgata", "plant_name_scientific": "chondrophora virgata", "plant_url": "herbs/chondrophora-virgata.html", "title": "chondrophora virgata", "intro": "Chondrophora virgata is a plant species in the family Boraginaceae, commonly known as the boraginaceae or forget-me-not family. It is a flowering plant native to the tropical regions of Asia and Australia, and has been used in traditional medicine for centuries. Chondrophora virgata has been found to possess medicinal properties, including anti-inflammatory and antioxidant effects, which have been attributed to its ability to reduce inflammation and protect cells from oxidative damage. The plant can be prepared as a herbal remedy through infusions or decoctions, and has been traditionally used to treat various health conditions, including fever, rheumatism, and digestive issues."}