{"plant_slug": "coronopus-didymus-var-incisus", "plant_name_scientific": "coronopus didymus var. incisus", "plant_url": "herbs/coronopus-didymus-var-incisus.html", "title": "coronopus didymus var. incisus", "intro": "Coronopus didymus var. incisus, also known as Least Swinecress, is a perennial plant species belonging to the Brassicaceae family, characterized by its small, white or pink flowers and lobed or incised leaves. The plant has been used in traditional medicine due to its potential medicinal properties, including anti-inflammatory and antimicrobial activities. The health benefits of Coronopus didymus var. incisus include its ability to reduce inflammation, improve wound healing, and exhibit antiseptic properties, making it a potential remedy for various skin conditions and infections. The plant can be prepared into herbal remedies such as infusions, decoctions, or tinctures, which can be used to leverage its medicinal and health benefits."}