{"plant_slug": "coryphopteris-diaphana", "plant_name_scientific": "coryphopteris diaphana", "plant_url": "herbs/coryphopteris-diaphana.html", "title": "coryphopteris diaphana", "intro": "Coryphopteris diaphana, also known as the Diaphanous Coryphopteris or Diaphanous Holly Fern, is a species of plant in the family Dryopteridaceae, characterized by its delicate and lacy fronds. Traditionally, Coryphopteris diaphana has been used in herbal medicine for its medicinal properties, which include anti-inflammatory, antimicrobial, and antioxidant effects. The health benefits of Coryphopteris diaphana are said to include reducing inflammation, improving respiratory issues, and supporting immune function. In herbal preparations, the plant's leaves can be used to make teas, infusions, and tinctures, although its use is not well-documented and may require further research for confirmation of safety and efficacy."}