{"plant_slug": "eriocaulon-fergusonii", "plant_name_scientific": "eriocaulon fergusonii", "plant_url": "herbs/eriocaulon-fergusonii.html", "title": "eriocaulon fergusonii", "intro": "Eriocaulon fergusonii is a species of flowering plant in the family Eriocaulaceae, commonly known as the pipefish cattail, and is native to India. This plant has been traditionally used for its medicinal properties, including its anti-inflammatory and antimicrobial effects. The health benefits of Eriocaulon fergusonii include its potential to treat various ailments, such as fever, cold, and respiratory infections, due to its expectorant properties. Eriocaulon fergusonii can be prepared as a decoction or infusion, and its leaves and rhizomes are often used in herbal preparations to harness its medicinal properties."}