{"plant_slug": "euonymus-alatus-var-arakianus", "plant_name_scientific": "euonymus alatus var. arakianus", "plant_url": "herbs/euonymus-alatus-var-arakianus.html", "title": "euonymus alatus var. arakianus", "intro": "Euonymus alatus var. arakianus, also known as Spotted-leaf Euonymus, is a deciduous shrub native to China, characterized by its distinctive pink or reddish-brown spots on its leaves. The plant is traditionally used in herbal medicine for its anti-inflammatory, antiseptic, and analgesic properties, which can help to alleviate symptoms of fever, rheumatism, and skin conditions. The health benefits of Euonymus alatus var. arakianus include reducing inflammation and pain, as well as promoting wound healing and immune system function. In herbal preparations, the plant can be used to make teas, infusions, or tinctures, which can be taken orally to harness its medicinal properties."}