{"plant_slug": "exochaenium-clavatum-subsp-stella-palustre", "plant_name_scientific": "exochaenium clavatum subsp. stella-palustre", "plant_url": "herbs/exochaenium-clavatum-subsp-stella-palustre.html", "title": "exochaenium clavatum subsp. stella-palustre", "intro": "Exochaenium clavatum subsp. stella-palustre is a rare and endemic subspecies of flowering plant native to Madagascar. This plant has been used in traditional medicine for its medicinal properties, including anti-inflammatory and antiseptic properties, which can be beneficial in treating wounds, fever, and various infections. Exochaenium clavatum subsp. stella-palustre has been used to treat a variety of health issues, including digestive problems, respiratory issues, and skin conditions, due to its antioxidant and antimicrobial properties. Herbal preparations of this plant are typically made by infusing the leaves in hot water or by using it in a tincture form, and it is often used in combination with other herbs to enhance its medicinal effects."}