{"plant_slug": "hedypnois-pyrenaica", "plant_name_scientific": "hedypnois pyrenaica", "plant_url": "herbs/hedypnois-pyrenaica.html", "title": "hedypnois pyrenaica", "intro": "Hedypnois pyrenaica, also known as Pyrenean hedypnois or Saint Victor's spike, is a perennial herb native to the western Alps and Pyrenees. The medicinal properties of Hedypnois pyrenaica include its anti-inflammatory and antispasmodic effects, which are attributed to its saponin and flavonoid content. It has been traditionally used to treat various health issues, such as digestive problems, bronchitis, and menstrual cramps, due to its ability to relax the smooth muscles and reduce inflammation. Hedypnois pyrenaica can be prepared as an infusion, tincture, or decoction, allowing for its medicinal properties to be utilized in herbal remedies."}