{"plant_slug": "horkelia-parryi", "plant_name_scientific": "horkelia parryi", "plant_url": "herbs/horkelia-parryi.html", "title": "horkelia parryi", "intro": "Horkelia parryi, also known as Parry's Horkelia, is a perennial plant species native to the western United States and Canada. It has been used in traditional medicine for its anti-inflammatory and antimicrobial properties, which can be attributed to its rich content of flavonoids and phenolic acids. The plant is said to possess various health benefits, including reducing inflammation, improving cardiovascular health, and supporting immune function. Horkelia parryi can be prepared as an herbal tea, infusion, or tincture, and is often used in herbal medicine to promote overall well-being and resilience."}