{"plant_slug": "juniperus-silicicola", "plant_name_scientific": "juniperus silicicola", "plant_url": "herbs/juniperus-silicicola.html", "title": "juniperus silicicola", "intro": "Juniperus silicicola, also known as the Utah juniper, is a species of evergreen tree that is native to the southwestern United States. The plant has been used in traditional medicine for its medicinal properties, which include its antiseptic, anti-inflammatory, and diuretic properties. The health benefits of Juniperus silicicola include its ability to aid in digestion, relieve respiratory issues, and lower blood pressure. Juniperus silicicola can be prepared into various herbal forms, including teas, infusions, and tinctures, which can be used to harness its medicinal properties."}