{"plant_slug": "lachnostoma-tigrinum", "plant_name_scientific": "lachnostoma tigrinum", "plant_url": "herbs/lachnostoma-tigrinum.html", "title": "lachnostoma tigrinum", "intro": "Lachnostoma tigrinum, also known as the Tiger's Claw, is a species of orchid native to tropical regions of Central and South America. It is prized for its medicinal properties, which include anti-inflammatory, antibacterial, and antifungal properties. The health benefits of Lachnostoma tigrinum include its ability to treat wounds, reduce fever, and alleviate respiratory issues such as coughs and colds. The plant can be prepared as a herbal tea or tincture, allowing for the extraction and utilization of its medicinal compounds."}