{"plant_slug": "lespedeza-lichiyuniae", "plant_name_scientific": "lespedeza lichiyuniae", "plant_url": "herbs/lespedeza-lichiyuniae.html", "title": "lespedeza lichiyuniae", "intro": "Lespedeza lichiyuniae is a type of climbing legume plant native to China, belonging to the Fabaceae family. The plant has been traditionally used for its medicinal properties, which include anti-inflammatory, antibacterial, and antifungal activities. It is valued for its potential health benefits, such as reducing fever, treating respiratory issues, and supporting the immune system. Lespedeza lichiyuniae is often prepared as a tea or infusion, as well as being used in traditional Chinese medicine to create herbal remedies for various ailments."}