{"plant_slug": "limonium-cuspidatum", "plant_name_scientific": "limonium cuspidatum", "plant_url": "herbs/limonium-cuspidatum.html", "title": "limonium cuspidatum", "intro": "Limonium cuspidatum, also known as sea lavender or sea pinks, is a type of flowering plant that belongs to the Plumbaginaceae family. The plant has been used in traditional medicine for its medicinal properties, which include anti-inflammatory, antibacterial, and antifungal properties. The health benefits of Limonium cuspidatum include reducing inflammation and improving respiratory issues, such as bronchitis and asthma, as well as its ability to soothe digestive problems and promote wound healing. The plant is typically prepared as an herbal tea, infusion, or tincture, and can also be used in the form of essential oil for its therapeutic benefits."}