{"plant_slug": "lisowskia-physuroides", "plant_name_scientific": "lisowskia physuroides", "plant_url": "herbs/lisowskia-physuroides.html", "title": "lisowskia physuroides", "intro": "Lisowskia physuroides is a plant species belonging to the family Gentianaceae. It has been traditionally used for its medicinal properties, particularly in treating fever, rheumatic conditions, and inflammation. The plant contains compounds that exhibit anti-inflammatory, antimicrobial, and antioxidant activities, contributing to its various health benefits, including reducing pain and improving respiratory function. Lisowskia physuroides can be prepared into herbal teas, infusions, or extracts, which are commonly used in traditional medicine."}