{"plant_slug": "mammillaria-crinita-subsp-scheinvariana", "plant_name_scientific": "mammillaria crinita subsp. scheinvariana", "plant_url": "herbs/mammillaria-crinita-subsp-scheinvariana.html", "title": "mammillaria crinita subsp. scheinvariana", "intro": "Mammillaria crinita subsp. scheinvariana, also known as the Scheinvariana Pincushion Cactus, is a rare and endemic species of the Mammillaria crinita cactus, characterized by its unique and striking appearance. This plant is traditionally used in folk medicine for its medicinal properties, which include anti-inflammatory and antimicrobial effects. The health benefits of Mammillaria crinita subsp. scheinvariana include its potential to reduce inflammation, improve wound healing, and exhibit antioxidant properties. Herbal preparations of this plant can be made into teas, infusions, or tinctures, and are often used to treat various health conditions, although more research is needed to fully understand its effects and potential interactions."}