{"plant_slug": "mariscus-riparius-var-crassus", "plant_name_scientific": "mariscus riparius var. crassus", "plant_url": "herbs/mariscus-riparius-var-crassus.html", "title": "mariscus riparius var. crassus", "intro": "Mariscus riparius var. crassus, also known as a variant of the cattail or bulrush, is a type of aquatic plant that belongs to the sedge family. It has been used in traditional medicine for its medicinal properties, which include anti-inflammatory and antimicrobial effects. The health benefits of Mariscus riparius var. crassus include treating various conditions such as fever, rheumatism, and digestive issues, as well as its use as a diuretic. In herbal preparations, the plant's rhizomes and roots are typically harvested and dried for use in teas, infusions, and tinctures to harness its medicinal properties."}