{"plant_slug": "meibomia-polymorpha", "plant_name_scientific": "meibomia polymorpha", "plant_url": "herbs/meibomia-polymorpha.html", "title": "meibomia polymorpha", "intro": "Meibomia polymorpha, also known as Butterfly Weed, is a perennial wildflower native to North America, belonging to the milkweed family (Asclepiadaceae). The plant contains a range of medicinal properties, particularly its high concentration of alkaloids, which have anti-inflammatory, antiseptic, and antispasmodic effects. The health benefits of Meibomia polymorpha include reducing fever, relieving respiratory issues, and treating skin conditions, such as eczema and acne. The plant can be prepared into herbal teas, infusions, and tinctures for medicinal use, although it's essential to consult a medical professional before using it as a treatment."}