{"plant_slug": "melaleuca-concreta", "plant_name_scientific": "melaleuca concreta", "plant_url": "herbs/melaleuca-concreta.html", "title": "melaleuca concreta", "intro": "Melaleuca concreta, also known as the narrow-leaved melaleuca, is a species of flowering plant in the myrtle family. This plant has been used for its medicinal properties, particularly for its antibacterial and anti-inflammatory properties, which can be attributed to its essential oils. The health benefits of Melaleuca concreta include reducing fever and relieving coughs, as well as treating minor wounds and skin irritations. Herbal preparations of Melaleuca concreta can be made into teas, tinctures, and ointments, which can be used topically or taken internally to reap its medicinal benefits."}