{"plant_slug": "neochilenia-setosiflora-var-intermedia", "plant_name_scientific": "neochilenia setosiflora var. intermedia", "plant_url": "herbs/neochilenia-setosiflora-var-intermedia.html", "title": "neochilenia setosiflora var. intermedia", "intro": "Neochilenia setosiflora var. intermedia is a rare and lesser-known plant species belonging to the Brassicaceae family, which is native to the Andes mountains in South America. It is valued for its medicinal properties, particularly its anti-inflammatory and antimicrobial compounds, which have been traditionally used to treat various health conditions, including respiratory issues, digestive problems, and skin irritations. The plant's health benefits include its potential to reduce inflammation, improve immune function, and exhibit antioxidant properties, making it a sought-after ingredient in herbal remedies. Neochilenia setosiflora var. intermedia is often prepared in herbal teas, infusions, and tinctures, which can be consumed orally or applied topically to the skin, depending on the specific health concern being addressed.", "medicine_or_poison": [{"medicine_or_poison": "poison", "mentions": 7, "confidence_score": 67, "total_score": 469}, {"medicine_or_poison": "medicine", "mentions": 3, "confidence_score": 24, "total_score": 72}]}