{"plant_slug": "neogaillonia-eriantha", "plant_name_scientific": "neogaillonia eriantha", "plant_url": "herbs/neogaillonia-eriantha.html", "title": "neogaillonia eriantha", "intro": "Neogaillonia eriantha is a rare and endangered flowering plant species that belongs to the family Fabaceae. This plant is known for its medicinal properties, including its ability to exhibit anti-inflammatory and antioxidant activities, making it a potential remedy for various health issues. The health benefits of Neogaillonia eriantha include its potential to treat conditions such as fever, rheumatism, and skin disorders. Herbal preparations of Neogaillonia eriantha include infusions, decoctions, and tinctures, which can be used to harness its medicinal properties and promote overall well-being."}