{"plant_slug": "ochna-elongata", "plant_name_scientific": "ochna elongata", "plant_url": "herbs/ochna-elongata.html", "title": "ochna elongata", "intro": "Ochna elongata, also known as the Mickey Mouse plant, is a species of flowering plant in the family Ochnaceae. It is native to tropical Africa and has been used in traditional medicine for its medicinal properties, including its ability to treat fever, rheumatism, and skin conditions. The plant is rich in flavonoids and phenolic compounds, which have been shown to have antioxidant, anti-inflammatory, and antimicrobial properties, providing various health benefits such as reducing oxidative stress, improving cardiovascular health, and supporting immune function. The plant can be prepared into herbal teas, infusions, and tinctures, which are used to harness its medicinal properties and provide relief from various health issues."}