{"plant_slug": "odontostemma-yunnanense", "plant_name_scientific": "odontostemma yunnanense", "plant_url": "herbs/odontostemma-yunnanense.html", "title": "odontostemma yunnanense", "intro": "Odontostemma yunnanense, also known as Yunnan odontostemma, is a species of flowering plant in the family Plantaginaceae. It is a perennial herb used in traditional Chinese medicine, where it is valued for its medicinal properties. The plant is said to have anti-inflammatory, antioxidant, and anti-bacterial properties, which can help to reduce fever, relieve pain, and promote healing. Odontostemma yunnanense is commonly used in herbal preparations such as decoctions, infusions, and tinctures, which are believed to provide various health benefits, including reducing inflammation, improving digestion, and boosting the immune system."}