{"plant_slug": "oncidium-uhlii", "plant_name_scientific": "oncidium uhlii", "plant_url": "herbs/oncidium-uhlii.html", "title": "oncidium uhlii", "intro": "Oncidium uhlii, also known as the 'Dancing Lady' orchid, is a species of epiphytic orchid native to Central and South America. The plant has been used in traditional medicine for its medicinal properties, including anti-inflammatory, antiseptic, and antimicrobial properties, which are attributed to its high concentration of flavonoids and phenolic acids. The health benefits of Oncidium uhlii include its potential to reduce inflammation, improve cardiovascular health, and exhibit antioxidant properties, making it a valuable herbal remedy for various ailments. Oncidium uhlii can be prepared into herbal teas, infusions, or tinctures, which can be used to harness its medicinal properties and health benefits."}