{"plant_slug": "orphanodendron-grandiflorum-var-grandiflorum", "plant_name_scientific": "orphanodendron grandiflorum var. grandiflorum", "plant_url": "herbs/orphanodendron-grandiflorum-var-grandiflorum.html", "title": "orphanodendron grandiflorum var. grandiflorum", "intro": "Orphanodendron grandiflorum var. grandiflorum, a lesser-known species of flowering plant in the family Icacinaceae, is also known as the \"Queen of the Night\" due to its nocturnal blooming habit. The plant has been found to possess medicinal properties, including anti-inflammatory and antioxidant activities, which have been attributed to the presence of various bioactive compounds. The health benefits of Orphanodendron grandiflorum var. grandiflorum include its potential to lower blood pressure, improve cardiovascular health, and exhibit antimicrobial properties. Herbal preparations of the plant, such as teas and infusions, have been traditionally used in folk medicine, although further research is needed to confirm its efficacy and safety for human consumption."}