{"plant_slug": "phreatia-kempteri", "plant_name_scientific": "phreatia kempteri", "plant_url": "herbs/phreatia-kempteri.html", "title": "phreatia kempteri", "intro": "Phreatia kempteri, also known as the Kempter's phreatia, is a species of orchid that belongs to the family Orchidaceae. The plant is traditionally used in various cultures for its medicinal properties, particularly in the treatment of fever, rheumatism, and digestive issues. The medicinal properties of Phreatia kempteri are attributed to its anti-inflammatory and antipyretic compounds, which help to reduce pain and alleviate symptoms associated with various health conditions. Herbal preparations of the plant include infusions and decoctions, which can be used to treat a range of health issues, including fever, cough, and skin problems."}