{"plant_slug": "platyschkuhria-integrifolia-var-oblongifolia", "plant_name_scientific": "platyschkuhria integrifolia var. oblongifolia", "plant_url": "herbs/platyschkuhria-integrifolia-var-oblongifolia.html", "title": "platyschkuhria integrifolia var. oblongifolia", "intro": "Platyschkuhria integrifolia var. oblongifolia, commonly known as a type of flowering plant, is a member of the Asteraceae family. This plant has been used in traditional medicine for its various health benefits, including its anti-inflammatory and antioxidant properties, which may help reduce pain and improve overall well-being. The therapeutic actions of Platyschkuhria integrifolia var. oblongifolia include analgesic, anti-inflammatory, and antimicrobial effects, making it a potential remedy for various health issues. The bioactive constituents of this plant include sesquiterpene lactones and phenolic compounds, which may contribute to its medicinal properties.", "benefits": "Platyschkuhria integrifolia var. oblongifolia has many benefits, such as its antioxidant properties, which help to reduce inflammation and protect against cell damage, improving overall health and increasing the body's resistance to diseases like cancer and cardiovascular disease. This plant also has antimicrobial properties, which aid in fighting off infections and promoting wound healing, as well as reducing the severity of symptoms associated with conditions like arthritis and diabetes. Additionally, Platyschkuhria integrifolia var. oblongifolia has been found to have anti-inflammatory properties, which help to alleviate symptoms of conditions like asthma, allergies, and digestive issues, thereby improving the quality of life for individuals suffering from these conditions. By incorporating Platyschkuhria integrifolia var. oblongifolia into one's diet or using it as a medicinal treatment, individuals can experience improved physical and mental well-being, enhanced cognitive function, and a reduced risk of chronic diseases.", "actions": "", "medicine_or_poison": [{"medicine_or_poison": "medicine", "mentions": 5, "confidence_score": 37, "total_score": 185}, {"medicine_or_poison": "poison", "mentions": 5, "confidence_score": 22, "total_score": 110}], "constituents": "", "parts": "", "preparations": "", "side_effects": ""}