{"plant_slug": "polygala-santanderensis", "plant_name_scientific": "polygala santanderensis", "plant_url": "herbs/polygala-santanderensis.html", "title": "polygala santanderensis", "intro": "Polygala santanderensis, also known as the Santander polygala, is a plant species belonging to the Polygalaceae family. It is traditionally used for its medicinal properties, particularly in the treatment of various health conditions, including fever, rheumatism, and respiratory issues. The plant is rich in flavonoids, phenolic acids, and other bioactive compounds, which contribute to its health benefits such as anti-inflammatory, antioxidant, and immunomodulatory effects. The herbal preparations of Polygala santanderensis include infusions, decoctions, and tinctures, which can be used to promote overall well-being and alleviate symptoms associated with certain health conditions."}