{"plant_slug": "polygala-gracilenta", "plant_name_scientific": "polygala gracilenta", "plant_url": "herbs/polygala-gracilenta.html", "title": "polygala gracilenta", "intro": "Polygala gracilenta, also known as Yac\u00f3n root, is a perennial plant native to the Andean region of South America. This plant has been traditionally used for its medicinal properties, which include anti-inflammatory, antioxidant, and antimicrobial effects. The health benefits of Polygala gracilenta include its potential to lower blood sugar levels, reduce blood pressure, and improve digestion. The plant can be prepared as an herbal tea, tincture, or supplement, and is also used in traditional medicine to treat various ailments, including gastrointestinal issues and respiratory problems."}