{"plant_slug": "pouzolzia-guatemalana-var-guatemalana", "plant_name_scientific": "pouzolzia guatemalana var. guatemalana", "plant_url": "herbs/pouzolzia-guatemalana-var-guatemalana.html", "title": "pouzolzia guatemalana var. guatemalana", "intro": "Pouzolzia guatemalana var. guatemalana, also known as the Guatemalan Pouzolzia, is a plant species belonging to the Euphorbiaceae family. It has been traditionally used in herbal medicine due to its medicinal properties, which include anti-inflammatory and antimicrobial activities. The health benefits associated with Pouzolzia guatemalana var. guatemalana include relief from fever, rheumatism, and digestive issues, as well as its potential to reduce pain and inflammation. Pouzolzia guatemalana var. guatemalana can be prepared for medicinal use through various herbal preparations, such as infusions, decoctions, and tinctures."}