{"plant_slug": "quiina-berryi", "plant_name_scientific": "quiina berryi", "plant_url": "herbs/quiina-berryi.html", "title": "quiina berryi", "intro": "Quiina berryi, also known as the Quiina tree, is a plant species native to South America, belonging to the family Clusiaceae. The Quiina berryi plant has been traditionally used for its medicinal properties, which include anti-inflammatory and antimicrobial activities. The health benefits of Quiina berryi include its potential to treat various health conditions, such as fever, rheumatism, and skin infections, due to its antipyretic and antiseptic properties. Herbal preparations of Quiina berryi can be made into teas, infusions, or tinctures, allowing for its medicinal properties to be utilized for therapeutic purposes."}