{"plant_slug": "rapanea-avenis", "plant_name_scientific": "rapanea avenis", "plant_url": "herbs/rapanea-avenis.html", "title": "rapanea avenis", "intro": "Rapanea avenis, a species of flowering plant in the family Myrsinaceae, is a shrub native to the Pacific Islands. The plant has been traditionally used in Polynesian medicine, and its leaves are rich in medicinal properties, including antibacterial and anti-inflammatory compounds. The health benefits of Rapanea avenis include reducing fever, relieving joint pain, and treating respiratory issues such as bronchitis and asthma. Traditionally, the leaves are made into teas, infusions, or ointments for various herbal preparations, although the exact methods may vary depending on the specific culture and region."}