{"plant_slug": "rosa-opaciformis", "plant_name_scientific": "rosa opaciformis", "plant_url": "herbs/rosa-opaciformis.html", "title": "rosa opaciformis", "intro": "Rosa opaciformis is a species of flowering plant in the rose family, characterized by its small, pale yellow to white flowers and leathery, dark green leaves. The plant is valued for its medicinal properties, which include anti-inflammatory, antimicrobial, and antioxidant activities. Rosa opaciformis is believed to offer various health benefits, such as reducing inflammation and improving digestion, as well as supporting the immune system and reducing oxidative stress. Herbal preparations of Rosa opaciformis can be made into teas, infusions, or tinctures, and are often used in traditional medicine to promote overall well-being and alleviate various health conditions."}