{"plant_slug": "rubus-lucens-subsp-clementis", "plant_name_scientific": "rubus lucens subsp. clementis", "plant_url": "herbs/rubus-lucens-subsp-clementis.html", "title": "rubus lucens subsp. clementis", "intro": "Rubus lucens subsp. clementis, also known as the Tasmanian bramble or Tasmanian blackberry, is a subspecies of bramble native to Tasmania. It has been used in traditional medicine for its medicinal properties, including anti-inflammatory and antimicrobial effects. The health benefits of Rubus lucens subsp. clementis include its potential to reduce inflammation, improve cardiovascular health, and exhibit antioxidant properties. Herbal preparations of this plant, such as teas, infusions, and tinctures, are traditionally used to support overall well-being and alleviate various health issues."}