{"plant_slug": "sarcococca-coriacea", "plant_name_scientific": "sarcococca coriacea", "plant_url": "herbs/sarcococca-coriacea.html", "title": "sarcococca coriacea", "intro": "Sarcococca coriacea, also known as Christmas box, is a flowering plant species in the family Buxaceae. The plant has been traditionally used in herbal medicine, where its medicinal properties include anti-inflammatory, antimicrobial, and antioxidant effects, which contribute to its potential health benefits such as reducing inflammation and improving immune function. The health benefits of Sarcococca coriacea include its ability to support cardiovascular health, reduce stress and anxiety, and have antiseptic properties. The plant can be prepared for medicinal use through herbal preparations such as teas, infusions, and tinctures, although it is essential to consult with a healthcare professional before using it for medicinal purposes."}