{"plant_slug": "schefflera-littoralis", "plant_name_scientific": "schefflera littoralis", "plant_url": "herbs/schefflera-littoralis.html", "title": "schefflera littoralis", "intro": "Schefflera littoralis, also known as the umbrella plant or Australian schefflera, is a flowering plant native to Australia and New Guinea, characterized by its distinctive umbrella-like leaves. Traditionally, the plant has been used in folk medicine for its medicinal properties, including its anti-inflammatory and antimicrobial effects, which have been attributed to the presence of flavonoids and phenolic compounds. The health benefits of Schefflera littoralis include its potential to reduce stress and anxiety, improve sleep quality, and support immune function, although more research is needed to confirm its efficacy. In herbal preparations, the plant is often used in infusions or decoctions to make teas or tinctures, which can be consumed to take advantage of its medicinal properties."}