{"plant_slug": "schisandra-propinqua-subsp-intermedia", "plant_name_scientific": "schisandra propinqua subsp. intermedia", "plant_url": "herbs/schisandra-propinqua-subsp-intermedia.html", "title": "schisandra propinqua subsp. intermedia", "intro": "Schisandra propinqua subsp. intermedia, also known as the Intermediate Schisandra, is a species of flowering plant in the Schisandraceae family, native to the mountainous regions of East Asia. This plant is valued for its medicinal properties, which include adaptogenic, antioxidant, and anti-inflammatory compounds that have been traditionally used to boost the immune system, improve cognitive function, and enhance overall well-being. The health benefits of Schisandra propinqua subsp. intermedia are attributed to its ability to protect against oxidative stress, improve cardiovascular health, and support the body's natural detoxification processes. In traditional Chinese medicine, Schisandra propinqua subsp. intermedia is prepared as a decoction, tincture, or tea, and is also used in modern herbal medicine formulations to promote vitality and resilience."}