{"plant_slug": "sheadendron-paniculatum-var-virgatum", "plant_name_scientific": "sheadendron paniculatum var. virgatum", "plant_url": "herbs/sheadendron-paniculatum-var-virgatum.html", "title": "sheadendron paniculatum var. virgatum", "intro": "Sheadendron paniculatum var. virgatum, also known as the Chinese panax or Ligusticum, is a type of plant native to East Asia, specifically China and Korea. It belongs to the carrot family and is known for its medicinal properties, particularly its ability to act as an antispasmodic, anti-inflammatory, and antioxidant. The plant is rich in bioactive compounds such as ligustilide, which provides numerous health benefits, including reducing inflammation, improving cardiovascular health, and aiding in digestion. Sheadendron paniculatum var. virgatum can be prepared into herbal teas, infusions, or tinctures, making it a popular ingredient in traditional Chinese medicine and modern herbal remedies."}