{"plant_slug": "sorengia-anceps", "plant_name_scientific": "sorengia anceps", "plant_url": "herbs/sorengia-anceps.html", "title": "sorengia anceps", "intro": "Sorengia anceps is a flowering plant species belonging to the family Apiaceae, commonly found in the mountainous regions of Central Asia. It has been traditionally used for its medicinal properties, which include anti-inflammatory, antioxidant, and antimicrobial effects, making it useful in treating various health conditions. The health benefits of Sorengia anceps include its potential to reduce inflammation and improve respiratory issues, as well as its ability to support immune function and protect against oxidative stress. Sorengia anceps is typically used in herbal preparations such as teas, infusions, and tinctures, and its extracts have also been studied for their potential use in pharmaceutical applications.", "medicine_or_poison": [{"medicine_or_poison": "poison", "mentions": 8, "confidence_score": 78, "total_score": 624}, {"medicine_or_poison": "medicine", "mentions": 2, "confidence_score": 17, "total_score": 34}]}