{"plant_slug": "stevia-morii", "plant_name_scientific": "stevia morii", "plant_url": "herbs/stevia-morii.html", "title": "stevia morii", "intro": "Stevia morii, also known as the sweet leaf, is a type of plant native to the tropical regions of Central and South America. It is a member of the sunflower family and is known for its natural sweetness due to the presence of stevioside and rebaudioside, compounds that are up to 300 times sweeter than sugar. The medicinal properties of Stevia morii include its ability to regulate blood sugar levels, lower blood pressure, and act as an anti-inflammatory agent. The health benefits of Stevia morii include weight loss, improved dental health, and reduced risk of heart disease, and it is often consumed as a herbal tea, capsule, or powder."}