{"plant_slug": "sulcorebutia-verticillacantha-var-albispina", "plant_name_scientific": "sulcorebutia verticillacantha var. albispina", "plant_url": "herbs/sulcorebutia-verticillacantha-var-albispina.html", "title": "sulcorebutia verticillacantha var. albispina", "intro": "Sulcorebutia verticillacantha var. albispina, also known as a cactus species, is a type of flowering plant that belongs to the Cactaceae family and is native to South America. This plant has been used in traditional medicine for its medicinal properties, which include anti-inflammatory and antioxidant effects, making it useful for treating various health conditions. The health benefits of Sulcorebutia verticillacantha var. albispina include its potential to reduce pain and inflammation, improve immune function, and even have antiviral and antibacterial properties. Sulcorebutia verticillacantha var. albispina is often used in herbal preparations, including teas, infusions, and tinctures, which are made by extracting its active compounds through various methods such as infusion, decoction, or solvent extraction."}