{"plant_slug": "syzygium-valdepunctatum", "plant_name_scientific": "syzygium valdepunctatum", "plant_url": "herbs/syzygium-valdepunctatum.html", "title": "syzygium valdepunctatum", "intro": "Syzygium valdepunctatum, also known as the 'Pointed Syzygium' or 'Syzygium punctatum,' is a species of flowering plant in the family Myrtaceae. This plant has been used in traditional medicine for its medicinal properties, which include antibacterial, anti-inflammatory, and antioxidant effects. The health benefits of Syzygium valdepunctatum include its potential to treat various ailments, such as fever, cough, and respiratory issues, as well as its ability to support immune function and reduce oxidative stress. In herbal preparations, Syzygium valdepunctatum is often used in teas, infusions, and decoctions, as well as in topical applications to soothe skin irritations and wounds."}