{"plant_slug": "taonabo-elongata", "plant_name_scientific": "taonabo elongata", "plant_url": "herbs/taonabo-elongata.html", "title": "taonabo elongata", "intro": "Taonabo elongata is a plant species that belongs to the Euphorbiaceae family, commonly found in the tropical regions of Southeast Asia and the Pacific Islands. It has been traditionally used for its medicinal properties, including anti-inflammatory and antimicrobial properties, which are attributed to the presence of flavonoids and terpenoids. The plant is valued for its health benefits, such as reducing fever and relieving pain, and is also used to treat various skin conditions, including wounds and infections. Taonabo elongata is typically prepared as a decoction or infusion for its herbal remedies, and its extracts have also been studied for their potential uses in modern medicine.", "benefits": "", "actions": "", "medicine_or_poison": [{"medicine_or_poison": "poison", "mentions": 10, "confidence_score": 43, "total_score": 430}], "constituents": ""}