{"plant_slug": "tapirira-pilosa", "plant_name_scientific": "tapirira pilosa", "plant_url": "herbs/tapirira-pilosa.html", "title": "tapirira pilosa", "intro": "Tapirira pilosa, also known as \"Cabe\u00e7a de Vaca,\" is a tropical plant species native to the Amazon rainforest, belonging to the Annonaceae family. The plant is valued for its medicinal properties, including anti-inflammatory and antimicrobial properties, which are attributed to the presence of various alkaloids and lignans. The health benefits of Tapirira pilosa include its potential to aid in wound healing, reduce fever, and alleviate respiratory issues, making it a valuable remedy in traditional medicine. Herbal preparations of the plant can be found in various forms, including teas, infusions, and extracts, which are used to harness its medicinal properties and promote overall well-being."}