{"plant_slug": "xanthomyrtus-arfakensis", "plant_name_scientific": "xanthomyrtus arfakensis", "plant_url": "herbs/xanthomyrtus-arfakensis.html", "title": "xanthomyrtus arfakensis", "intro": "Xanthomyrtus arfakensis is a species of flowering plant in the family Myrtaceae, commonly known as the Arfak myrtle. The plant has been found to possess medicinal properties, particularly in its ability to exhibit antimicrobial and antifungal activities. The health benefits of Xanthomyrtus arfakensis include its potential to treat various infections and wounds due to its antimicrobial properties. Herbal preparations of the plant are often used in traditional medicine, typically in the form of infusions or decoctions, although further research is needed to fully understand its uses and effects."}